shira/__init__.py
shira/_search.py
shira/shira.py
shira/shira.scss
shira-0.1.0a0.dist-info/entry_points.txt
shira-0.1.0a0.dist-info/WHEEL
shira-0.1.0a0.dist-info/METADATA
shira-0.1.0a0.dist-info/RECORD
