Metadata-Version: 2.1
Name: shira
Version: 0.1.0a0
Summary: Investigate!
Author: Darren Burns
Author-email: darrenb900@gmail.com
Requires-Python: >=3.10,<4.0
Classifier: Programming Language :: Python :: 3
Classifier: Programming Language :: Python :: 3.10
Classifier: Programming Language :: Python :: 3.11
Requires-Dist: textual[dev] (>=0.4.0,<0.5.0)
